genovis/__init__.py
genovis/__main__.py
genovis/admix.py
genovis/manplot.py
genovis/mapden.py
genovis/pca3d.py
genovis/relmap.py
genovis/rohpainter.py
genovis/gui/__init__.py
genovis/gui/genovis_gui.py
genovis/gui/main.py
genovis/gui/resources/GENOVIS.ico
genovis/gui/resources/GENOVIS.png
genovis-1.0.5.dist-info/licenses/LICENSE.txt
genovis-1.0.5.dist-info/METADATA
genovis-1.0.5.dist-info/WHEEL
genovis-1.0.5.dist-info/entry_points.txt
genovis-1.0.5.dist-info/top_level.txt
genovis-1.0.5.dist-info/RECORD
