Metadata-Version: 2.4
Name: genovis
Version: 1.0.5
Summary: GENOVIS: Population genomics visualization toolkit
License: MIT License for GENOVIS
Requires-Python: >=3.9
License-File: LICENSE.txt
Requires-Dist: numpy
Requires-Dist: pandas
Requires-Dist: matplotlib
Requires-Dist: seaborn
Requires-Dist: PyQt5>=5.15
Dynamic: license-file
